{
	"name": "ds_controltable",
	"properties": {
		"linkedServiceName": {
			"referenceName": "ls_controltable",
			"type": "LinkedServiceReference"
		},
		"annotations": [],
		"type": "AzureSqlTable",
		"schema": [
			{
				"name": "TableName",
				"type": "nvarchar"
			},
			{
				"name": "LastProcessedTimestamp",
				"type": "datetime",
				"precision": 23,
				"scale": 3
			}
		],
		"typeProperties": {
			"schema": "dbo",
			"table": "ControlTable"
		}
	},
	"type": "Microsoft.DataFactory/factories/datasets"
}